linkup/__init__.py
linkup/base.py
linkup-0.0.3.dist-info/LICENSE
linkup-0.0.3.dist-info/METADATA
linkup-0.0.3.dist-info/WHEEL
linkup-0.0.3.dist-info/top_level.txt
linkup-0.0.3.dist-info/RECORD
