Metadata-Version: 2.1
Name: linkup
Version: 0.0.3
Summary: Making mappings operable.
Home-page: https://github.com/otosense/linkup
Author: OtoSense
License: apache-2.0
Platform: any
